{
	"name": "cdc-pipeline-v2",
	"properties": {
		"activities": [
			{
				"name": "cdcLookup",
				"type": "Lookup",
				"dependsOn": [],
				"policy": {
					"timeout": "0.12:00:00",
					"retry": 0,
					"retryIntervalInSeconds": 30,
					"secureOutput": false,
					"secureInput": false
				},
				"userProperties": [],
				"typeProperties": {
					"source": {
						"type": "JsonSource",
						"storeSettings": {
							"type": "AzureBlobFSReadSettings",
							"recursive": true,
							"enablePartitionDiscovery": false
						},
						"formatSettings": {
							"type": "JsonReadSettings"
						}
					},
					"dataset": {
						"referenceName": "ds_source_cdc_v2",
						"type": "DatasetReference"
					},
					"firstRowOnly": false
				}
			},
			{
				"name": "TotalCounts",
				"type": "Script",
				"dependsOn": [
					{
						"activity": "cdcLookup",
						"dependencyConditions": [
							"Succeeded"
						]
					}
				],
				"policy": {
					"timeout": "0.12:00:00",
					"retry": 0,
					"retryIntervalInSeconds": 30,
					"secureOutput": false,
					"secureInput": false
				},
				"userProperties": [],
				"linkedServiceName": {
					"referenceName": "ls_sqldbv2",
					"type": "LinkedServiceReference"
				},
				"typeProperties": {
					"scripts": [
						{
							"type": "Query",
							"text": {
								"value": "Select count(*) as Total_Count from @{pipeline().parameters.schema}.@{pipeline().parameters.table} where last_updated >'@{IF(empty(pipeline().parameters.BackDate),activity('cdcLookup').output.value[0].cdc_timestamp,pipeline().parameters.BackDate)}'\n",
								"type": "Expression"
							}
						}
					],
					"scriptBlockExecutionTimeout": "02:00:00"
				}
			},
			{
				"name": "If New Rows",
				"type": "IfCondition",
				"dependsOn": [
					{
						"activity": "TotalCounts",
						"dependencyConditions": [
							"Succeeded"
						]
					}
				],
				"userProperties": [],
				"typeProperties": {
					"expression": {
						"value": "@greater(activity('TotalCounts').output.resultSets[0].rows[0].Total_Count,0)",
						"type": "Expression"
					},
					"ifTrueActivities": [
						{
							"name": "Load",
							"type": "Copy",
							"dependsOn": [],
							"policy": {
								"timeout": "0.12:00:00",
								"retry": 0,
								"retryIntervalInSeconds": 30,
								"secureOutput": false,
								"secureInput": false
							},
							"userProperties": [],
							"typeProperties": {
								"source": {
									"type": "AzureSqlSource",
									"sqlReaderQuery": {
										"value": "Select * from @{pipeline().parameters.schema}.@{pipeline().parameters.table} where last_updated >'@{IF(empty(pipeline().parameters.BackDate),activity('cdcLookup').output.value[0].cdc_timestamp,pipeline().parameters.BackDate)}'",
										"type": "Expression"
									},
									"queryTimeout": "02:00:00",
									"partitionOption": "None"
								},
								"sink": {
									"type": "ParquetSink",
									"storeSettings": {
										"type": "AzureBlobFSWriteSettings"
									},
									"formatSettings": {
										"type": "ParquetWriteSettings"
									}
								},
								"enableStaging": false,
								"translator": {
									"type": "TabularTranslator",
									"typeConversion": true,
									"typeConversionSettings": {
										"allowDataTruncation": true,
										"treatBooleanAsNumber": false
									}
								}
							},
							"inputs": [
								{
									"referenceName": "ds_databasev2",
									"type": "DatasetReference"
								}
							],
							"outputs": [
								{
									"referenceName": "ds_parquet",
									"type": "DatasetReference"
								}
							]
						},
						{
							"name": "max cdc date",
							"type": "Script",
							"dependsOn": [
								{
									"activity": "Load",
									"dependencyConditions": [
										"Succeeded"
									]
								}
							],
							"policy": {
								"timeout": "0.12:00:00",
								"retry": 0,
								"retryIntervalInSeconds": 30,
								"secureOutput": false,
								"secureInput": false
							},
							"userProperties": [],
							"linkedServiceName": {
								"referenceName": "ls_sqldbv2",
								"type": "LinkedServiceReference"
							},
							"typeProperties": {
								"scripts": [
									{
										"type": "Query",
										"text": {
											"value": "Select max(last_updated) as cdc_timestamp from @{pipeline().parameters.schema}.@{pipeline().parameters.table}",
											"type": "Expression"
										}
									}
								],
								"scriptBlockExecutionTimeout": "02:00:00"
							}
						},
						{
							"name": "Change cdc date",
							"type": "Copy",
							"dependsOn": [
								{
									"activity": "max cdc date",
									"dependencyConditions": [
										"Succeeded"
									]
								}
							],
							"policy": {
								"timeout": "0.12:00:00",
								"retry": 0,
								"retryIntervalInSeconds": 30,
								"secureOutput": false,
								"secureInput": false
							},
							"userProperties": [],
							"typeProperties": {
								"source": {
									"type": "JsonSource",
									"additionalColumns": [
										{
											"name": "cdc_timestamp",
											"value": {
												"value": "@activity('max cdc date').output.resultSets[0].rows[0].cdc_timestamp",
												"type": "Expression"
											}
										}
									],
									"storeSettings": {
										"type": "AzureBlobFSReadSettings",
										"recursive": true,
										"enablePartitionDiscovery": false
									},
									"formatSettings": {
										"type": "JsonReadSettings"
									}
								},
								"sink": {
									"type": "JsonSink",
									"storeSettings": {
										"type": "AzureBlobFSWriteSettings"
									},
									"formatSettings": {
										"type": "JsonWriteSettings"
									}
								},
								"enableStaging": false
							},
							"inputs": [
								{
									"referenceName": "ds_empty_json",
									"type": "DatasetReference"
								}
							],
							"outputs": [
								{
									"referenceName": "ds_source_cdc_v2",
									"type": "DatasetReference"
								}
							]
						}
					]
				}
			}
		],
		"parameters": {
			"Schema": {
				"type": "string",
				"defaultValue": "source"
			},
			"Table": {
				"type": "string",
				"defaultValue": "orders"
			},
			"BackDate": {
				"type": "string"
			}
		},
		"annotations": [],
		"lastPublishTime": "2026-06-22T04:20:11Z"
	},
	"type": "Microsoft.DataFactory/factories/pipelines"
}